lionscliapp/__init__.py
lionscliapp/application.py
lionscliapp/builtins.py
lionscliapp/cli_parsing.py
lionscliapp/cli_state.py
lionscliapp/config_io.py
lionscliapp/ctx.py
lionscliapp/declarations.py
lionscliapp/dispatch.py
lionscliapp/entrypoint.py
lionscliapp/execroot.py
lionscliapp/file_io.py
lionscliapp/override_inputs.py
lionscliapp/paths.py
lionscliapp/resolve_execroot.py
lionscliapp/runtime_state.py
lionscliapp-0.1.0.dist-info/licenses/LICENSE
lionscliapp-0.1.0.dist-info/METADATA
lionscliapp-0.1.0.dist-info/WHEEL
lionscliapp-0.1.0.dist-info/top_level.txt
lionscliapp-0.1.0.dist-info/RECORD
