Metadata-Version: 2.4
Name: lionscliapp
Version: 0.1.0
Summary: A humane CLI application framework
Author-email: Lion Kimbro <lionkimbro@gmail.com>
License: CC0-1.0
Project-URL: Homepage, https://github.com/LionKimbro/lionscliapp
Project-URL: Repository, https://github.com/LionKimbro/lionscliapp
Classifier: Programming Language :: Python :: 3
Classifier: Programming Language :: Python :: 3.10
Classifier: Programming Language :: Python :: 3.11
Classifier: Programming Language :: Python :: 3.12
Classifier: License :: CC0 1.0 Universal (CC0 1.0) Public Domain Dedication
Classifier: Operating System :: OS Independent
Requires-Python: >=3.10
License-File: LICENSE
Dynamic: license-file
